[
  {
    "id": 1,
    "parentId": 0,
    "name": "系统管理",
    "path": "/system",
    "component": null,
    "componentName": null,
    "icon": "system",
    "visible": true,
    "keepAlive": true,
    "alwaysShow": true,
    "children": [
      {
        "id": 100,
        "parentId": 1,
        "name": "用户管理",
        "path": "user",
        "component": "system/user/index",
        "componentName": "SystemUser",
        "icon": "user",
        "visible": true,
        "keepAlive": true,
        "alwaysShow": true,
        "children": null
      },
      {
        "id": 101,
        "parentId": 1,
        "name": "角色管理",
        "path": "role",
        "component": "system/role/index",
        "componentName": "SystemRole",
        "icon": "peoples",
        "visible": true,
        "keepAlive": true,
        "alwaysShow": true,
        "children": null
      },
      {
        "id": 102,
        "parentId": 1,
        "name": "菜单管理",
        "path": "menu",
        "component": "system/menu/index",
        "componentName": "SystemMenu",
        "icon": "tree-table",
        "visible": true,
        "keepAlive": true,
        "alwaysShow": true,
        "children": null
      },
      {
        "id": 103,
        "parentId": 1,
        "name": "部门管理",
        "path": "dept",
        "component": "system/dept/index",
        "componentName": "SystemDept",
        "icon": "tree",
        "visible": true,
        "keepAlive": true,
        "alwaysShow": true,
        "children": null
      },
      {
        "id": 104,
        "parentId": 1,
        "name": "岗位管理",
        "path": "post",
        "component": "system/post/index",
        "componentName": "SystemPost",
        "icon": "post",
        "visible": true,
        "keepAlive": true,
        "alwaysShow": true,
        "children": null
      },
      {
        "id": 105,
        "parentId": 1,
        "name": "字典管理",
        "path": "dict",
        "component": "system/dict/index",
        "componentName": "SystemDictType",
        "icon": "dict",
        "visible": true,
        "keepAlive": true,
        "alwaysShow": true,
        "children": null
      },
      {
        "id": 107,
        "parentId": 1,
        "name": "通知公告",
        "path": "notice",
        "component": "system/notice/index",
        "componentName": "SystemNotice",
        "icon": "message",
        "visible": true,
        "keepAlive": true,
        "alwaysShow": true,
        "children": null
      },
      {
        "id": 108,
        "parentId": 1,
        "name": "审计日志",
        "path": "log",
        "component": "",
        "componentName": null,
        "icon": "log",
        "visible": true,
        "keepAlive": true,
        "alwaysShow": true,
        "children": [
          {
            "id": 500,
            "parentId": 108,
            "name": "操作日志",
            "path": "operate-log",
            "component": "system/operatelog/index",
            "componentName": "SystemOperateLog",
            "icon": "form",
            "visible": true,
            "keepAlive": true,
            "alwaysShow": true,
            "children": null
          },
          {
            "id": 501,
            "parentId": 108,
            "name": "登录日志",
            "path": "login-log",
            "component": "system/loginlog/index",
            "componentName": "SystemLoginLog",
            "icon": "logininfor",
            "visible": true,
            "keepAlive": true,
            "alwaysShow": true,
            "children": null
          }
        ]
      },
      {
        "id": 1261,
        "parentId": 1,
        "name": "OAuth 2.0",
        "path": "oauth2",
        "component": null,
        "componentName": null,
        "icon": "people",
        "visible": true,
        "keepAlive": true,
        "alwaysShow": true,
        "children": [
          {
            "id": 1263,
            "parentId": 1261,
            "name": "应用管理",
            "path": "oauth2/application",
            "component": "system/oauth2/client/index",
            "componentName": "SystemOAuth2Client",
            "icon": "tool",
            "visible": true,
            "keepAlive": true,
            "alwaysShow": true,
            "children": null
          },
          {
            "id": 109,
            "parentId": 1261,
            "name": "令牌管理",
            "path": "token",
            "component": "system/oauth2/token/index",
            "componentName": "SystemTokenClient",
            "icon": "online",
            "visible": true,
            "keepAlive": true,
            "alwaysShow": true,
            "children": null
          }
        ]
      },
      {
        "id": 1093,
        "parentId": 1,
        "name": "短信管理",
        "path": "sms",
        "component": null,
        "componentName": null,
        "icon": "validCode",
        "visible": true,
        "keepAlive": true,
        "alwaysShow": true,
        "children": [
          {
            "id": 1094,
            "parentId": 1093,
            "name": "短信渠道",
            "path": "sms-channel",
            "component": "system/sms/channel/index",
            "componentName": "SystemSmsChannel",
            "icon": "phone",
            "visible": true,
            "keepAlive": true,
            "alwaysShow": true,
            "children": null
          },
          {
            "id": 1100,
            "parentId": 1093,
            "name": "短信模板",
            "path": "sms-template",
            "component": "system/sms/template/index",
            "componentName": "SystemSmsTemplate",
            "icon": "phone",
            "visible": true,
            "keepAlive": true,
            "alwaysShow": true,
            "children": null
          },
          {
            "id": 1107,
            "parentId": 1093,
            "name": "短信日志",
            "path": "sms-log",
            "component": "system/sms/log/index",
            "componentName": "SystemSmsLog",
            "icon": "phone",
            "visible": true,
            "keepAlive": true,
            "alwaysShow": true,
            "children": null
          }
        ]
      },
      {
        "id": 2130,
        "parentId": 1,
        "name": "邮箱管理",
        "path": "mail",
        "component": null,
        "componentName": null,
        "icon": "email",
        "visible": true,
        "keepAlive": true,
        "alwaysShow": true,
        "children": [
          {
            "id": 2131,
            "parentId": 2130,
            "name": "邮箱账号",
            "path": "mail-account",
            "component": "system/mail/account/index",
            "componentName": "SystemMailAccount",
            "icon": "user",
            "visible": true,
            "keepAlive": true,
            "alwaysShow": true,
            "children": null
          },
          {
            "id": 2136,
            "parentId": 2130,
            "name": "邮件模版",
            "path": "mail-template",
            "component": "system/mail/template/index",
            "componentName": "SystemMailTemplate",
            "icon": "education",
            "visible": true,
            "keepAlive": true,
            "alwaysShow": true,
            "children": null
          },
          {
            "id": 2141,
            "parentId": 2130,
            "name": "邮件记录",
            "path": "mail-log",
            "component": "system/mail/log/index",
            "componentName": "SystemMailLog",
            "icon": "log",
            "visible": true,
            "keepAlive": true,
            "alwaysShow": true,
            "children": null
          }
        ]
      },
      {
        "id": 2144,
        "parentId": 1,
        "name": "站内信管理",
        "path": "notify",
        "component": null,
        "componentName": null,
        "icon": "message",
        "visible": true,
        "keepAlive": true,
        "alwaysShow": true,
        "children": [
          {
            "id": 2145,
            "parentId": 2144,
            "name": "模板管理",
            "path": "notify-template",
            "component": "system/notify/template/index",
            "componentName": "SystemNotifyTemplate",
            "icon": "education",
            "visible": true,
            "keepAlive": true,
            "alwaysShow": true,
            "children": null
          },
          {
            "id": 2151,
            "parentId": 2144,
            "name": "消息记录",
            "path": "notify-message",
            "component": "system/notify/message/index",
            "componentName": "SystemNotifyMessage",
            "icon": "edit",
            "visible": true,
            "keepAlive": true,
            "alwaysShow": true,
            "children": null
          }
        ]
      },
      {
        "id": 1110,
        "parentId": 1,
        "name": "错误码管理",
        "path": "error-code",
        "component": "system/errorCode/index",
        "componentName": "SystemErrorCode",
        "icon": "code",
        "visible": true,
        "keepAlive": true,
        "alwaysShow": true,
        "children": null
      },
      {
        "id": 1247,
        "parentId": 1,
        "name": "敏感词管理",
        "path": "sensitive-word",
        "component": "system/sensitiveWord/index",
        "componentName": "SystemSensitiveWord",
        "icon": "education",
        "visible": true,
        "keepAlive": true,
        "alwaysShow": true,
        "children": null
      },
      {
        "id": 2083,
        "parentId": 1,
        "name": "地区管理",
        "path": "area",
        "component": "system/area/index",
        "componentName": "SystemArea",
        "icon": "row",
        "visible": true,
        "keepAlive": true,
        "alwaysShow": true,
        "children": null
      }
    ]
  },
  {
    "id": 2,
    "parentId": 0,
    "name": "基础设施",
    "path": "/infra",
    "component": null,
    "componentName": null,
    "icon": "monitor",
    "visible": true,
    "keepAlive": true,
    "alwaysShow": true,
    "children": [
      {
        "id": 115,
        "parentId": 2,
        "name": "代码生成",
        "path": "codegen",
        "component": "infra/codegen/index",
        "componentName": "InfraCodegen",
        "icon": "code",
        "visible": true,
        "keepAlive": true,
        "alwaysShow": true,
        "children": null
      },
      {
        "id": 1070,
        "parentId": 2,
        "name": "代码生成示例",
        "path": "test-demo",
        "component": "infra/testDemo/index",
        "componentName": null,
        "icon": "validCode",
        "visible": true,
        "keepAlive": true,
        "alwaysShow": true,
        "children": null
      },
      {
        "id": 1255,
        "parentId": 2,
        "name": "数据源配置",
        "path": "data-source-config",
        "component": "infra/dataSourceConfig/index",
        "componentName": "InfraDataSourceConfig",
        "icon": "rate",
        "visible": true,
        "keepAlive": true,
        "alwaysShow": true,
        "children": null
      },
      {
        "id": 114,
        "parentId": 2,
        "name": "表单构建",
        "path": "build",
        "component": "infra/build/index",
        "componentName": "InfraBuild",
        "icon": "build",
        "visible": true,
        "keepAlive": true,
        "alwaysShow": true,
        "children": null
      },
      {
        "id": 116,
        "parentId": 2,
        "name": "系统接口",
        "path": "swagger",
        "component": "infra/swagger/index",
        "componentName": "InfraSwagger",
        "icon": "swagger",
        "visible": true,
        "keepAlive": true,
        "alwaysShow": true,
        "children": null
      },
      {
        "id": 1076,
        "parentId": 2,
        "name": "数据库文档",
        "path": "db-doc",
        "component": "infra/dbDoc/index",
        "componentName": "InfraDBDoc",
        "icon": "table",
        "visible": true,
        "keepAlive": true,
        "alwaysShow": true,
        "children": null
      },
      {
        "id": 1243,
        "parentId": 2,
        "name": "文件管理",
        "path": "file",
        "component": null,
        "componentName": "",
        "icon": "download",
        "visible": true,
        "keepAlive": true,
        "alwaysShow": true,
        "children": [
          {
            "id": 1237,
            "parentId": 1243,
            "name": "文件配置",
            "path": "file-config",
            "component": "infra/fileConfig/index",
            "componentName": "InfraFileConfig",
            "icon": "config",
            "visible": true,
            "keepAlive": true,
            "alwaysShow": true,
            "children": null
          },
          {
            "id": 1090,
            "parentId": 1243,
            "name": "文件列表",
            "path": "file",
            "component": "infra/file/index",
            "componentName": "InfraFile",
            "icon": "upload",
            "visible": true,
            "keepAlive": true,
            "alwaysShow": true,
            "children": null
          }
        ]
      },
      {
        "id": 106,
        "parentId": 2,
        "name": "配置管理",
        "path": "config",
        "component": "infra/config/index",
        "componentName": "InfraConfig",
        "icon": "edit",
        "visible": true,
        "keepAlive": true,
        "alwaysShow": true,
        "children": null
      },
      {
        "id": 1083,
        "parentId": 2,
        "name": "API 日志",
        "path": "log",
        "component": null,
        "componentName": null,
        "icon": "log",
        "visible": true,
        "keepAlive": true,
        "alwaysShow": true,
        "children": [
          {
            "id": 1078,
            "parentId": 1083,
            "name": "访问日志",
            "path": "api-access-log",
            "component": "infra/apiAccessLog/index",
            "componentName": "InfraApiAccessLog",
            "icon": "log",
            "visible": true,
            "keepAlive": true,
            "alwaysShow": true,
            "children": null
          },
          {
            "id": 1084,
            "parentId": 1083,
            "name": "错误日志",
            "path": "api-error-log",
            "component": "infra/apiErrorLog/index",
            "componentName": "InfraApiErrorLog",
            "icon": "log",
            "visible": true,
            "keepAlive": true,
            "alwaysShow": true,
            "children": null
          }
        ]
      },
      {
        "id": 111,
        "parentId": 2,
        "name": "MySQL 监控",
        "path": "druid",
        "component": "infra/druid/index",
        "componentName": "InfraDruid",
        "icon": "druid",
        "visible": true,
        "keepAlive": true,
        "alwaysShow": true,
        "children": null
      },
      {
        "id": 113,
        "parentId": 2,
        "name": "Redis 监控",
        "path": "redis",
        "component": "infra/redis/index",
        "componentName": "InfraRedis",
        "icon": "redis",
        "visible": true,
        "keepAlive": true,
        "alwaysShow": true,
        "children": null
      },
      {
        "id": 112,
        "parentId": 2,
        "name": "Java 监控",
        "path": "admin-server",
        "component": "infra/server/index",
        "componentName": "InfraAdminServer",
        "icon": "server",
        "visible": true,
        "keepAlive": true,
        "alwaysShow": true,
        "children": null
      },
      {
        "id": 110,
        "parentId": 2,
        "name": "定时任务",
        "path": "job",
        "component": "infra/job/index",
        "componentName": "InfraJob",
        "icon": "job",
        "visible": true,
        "keepAlive": true,
        "alwaysShow": true,
        "children": null
      },
      {
        "id": 1077,
        "parentId": 2,
        "name": "监控平台",
        "path": "skywalking",
        "component": "infra/skywalking/index",
        "componentName": "InfraSkyWalking",
        "icon": "eye-open",
        "visible": true,
        "keepAlive": true,
        "alwaysShow": true,
        "children": null
      }
    ]
  },
  {
    "id": 1117,
    "parentId": 0,
    "name": "支付管理",
    "path": "/pay",
    "component": null,
    "componentName": null,
    "icon": "money",
    "visible": true,
    "keepAlive": true,
    "alwaysShow": true,
    "children": [
      {
        "id": 1179,
        "parentId": 1117,
        "name": "商户信息",
        "path": "merchant",
        "component": "pay/merchant/index",
        "componentName": "PayApp",
        "icon": "merchant",
        "visible": true,
        "keepAlive": true,
        "alwaysShow": true,
        "children": null
      },
      {
        "id": 1126,
        "parentId": 1117,
        "name": "应用信息",
        "path": "app",
        "component": "pay/app/index",
        "componentName": "PayMerchant",
        "icon": "table",
        "visible": true,
        "keepAlive": true,
        "alwaysShow": true,
        "children": null
      },
      {
        "id": 1173,
        "parentId": 1117,
        "name": "支付订单",
        "path": "order",
        "component": "pay/order/index",
        "componentName": "PayOrder",
        "icon": "pay",
        "visible": true,
        "keepAlive": true,
        "alwaysShow": true,
        "children": null
      },
      {
        "id": 1161,
        "parentId": 1117,
        "name": "退款订单",
        "path": "refund",
        "component": "pay/refund/index",
        "componentName": "PayRefund",
        "icon": "order",
        "visible": true,
        "keepAlive": true,
        "alwaysShow": true,
        "children": null
      },
      {
        "id": 2161,
        "parentId": 1117,
        "name": "接入示例",
        "path": "demo-order",
        "component": "pay/demo/index",
        "componentName": null,
        "icon": "drag",
        "visible": true,
        "keepAlive": true,
        "alwaysShow": true,
        "children": null
      }
    ]
  },
  {
    "id": 1281,
    "parentId": 0,
    "name": "报表管理",
    "path": "/report",
    "component": null,
    "componentName": null,
    "icon": "chart",
    "visible": true,
    "keepAlive": true,
    "alwaysShow": true,
    "children": [
      {
        "id": 1282,
        "parentId": 1281,
        "name": "报表设计器",
        "path": "jimu-report",
        "component": "report/jmreport/index",
        "componentName": "GoView",
        "icon": "example",
        "visible": true,
        "keepAlive": true,
        "alwaysShow": true,
        "children": null
      },
      {
        "id": 2153,
        "parentId": 1281,
        "name": "大屏设计器",
        "path": "go-view",
        "component": "report/goview/index",
        "componentName": "JimuReport",
        "icon": "dashboard",
        "visible": true,
        "keepAlive": true,
        "alwaysShow": true,
        "children": null
      }
    ]
  },
  {
    "id": 1185,
    "parentId": 0,
    "name": "工作流程",
    "path": "/bpm",
    "component": null,
    "componentName": null,
    "icon": "tool",
    "visible": true,
    "keepAlive": true,
    "alwaysShow": true,
    "children": [
      {
        "id": 1186,
        "parentId": 1185,
        "name": "流程管理",
        "path": "manager",
        "component": null,
        "componentName": null,
        "icon": "nested",
        "visible": true,
        "keepAlive": true,
        "alwaysShow": true,
        "children": [
          {
            "id": 1187,
            "parentId": 1186,
            "name": "流程表单",
            "path": "form",
            "component": "bpm/form/index",
            "componentName": "BpmForm",
            "icon": "form",
            "visible": true,
            "keepAlive": true,
            "alwaysShow": true,
            "children": null
          },
          {
            "id": 1209,
            "parentId": 1186,
            "name": "用户分组",
            "path": "user-group",
            "component": "bpm/group/index",
            "componentName": "BpmUserGroup",
            "icon": "people",
            "visible": true,
            "keepAlive": true,
            "alwaysShow": true,
            "children": null
          },
          {
            "id": 1193,
            "parentId": 1186,
            "name": "流程模型",
            "path": "model",
            "component": "bpm/model/index",
            "componentName": "BpmModel",
            "icon": "guide",
            "visible": true,
            "keepAlive": true,
            "alwaysShow": true,
            "children": null
          }
        ]
      },
      {
        "id": 1200,
        "parentId": 1185,
        "name": "任务管理",
        "path": "task",
        "component": null,
        "componentName": null,
        "icon": "cascader",
        "visible": true,
        "keepAlive": true,
        "alwaysShow": true,
        "children": [
          {
            "id": 1201,
            "parentId": 1200,
            "name": "我的流程",
            "path": "my",
            "component": "bpm/processInstance/index",
            "componentName": "BpmProcessInstance",
            "icon": "people",
            "visible": true,
            "keepAlive": true,
            "alwaysShow": true,
            "children": null
          },
          {
            "id": 1207,
            "parentId": 1200,
            "name": "待办任务",
            "path": "todo",
            "component": "bpm/task/todo/index",
            "componentName": "BpmTodoTask",
            "icon": "eye-open",
            "visible": true,
            "keepAlive": true,
            "alwaysShow": true,
            "children": null
          },
          {
            "id": 1208,
            "parentId": 1200,
            "name": "已办任务",
            "path": "done",
            "component": "bpm/task/done/index",
            "componentName": "BpmDoneTask",
            "icon": "eye",
            "visible": true,
            "keepAlive": true,
            "alwaysShow": true,
            "children": null
          }
        ]
      },
      {
        "id": 5,
        "parentId": 1185,
        "name": "OA 示例",
        "path": "oa",
        "component": null,
        "componentName": null,
        "icon": "people",
        "visible": true,
        "keepAlive": true,
        "alwaysShow": true,
        "children": [
          {
            "id": 1118,
            "parentId": 5,
            "name": "请假查询",
            "path": "leave",
            "component": "bpm/oa/leave/index",
            "componentName": "BpmOALeave",
            "icon": "user",
            "visible": true,
            "keepAlive": true,
            "alwaysShow": true,
            "children": null
          }
        ]
      }
    ]
  },
  {
    "id": 2000,
    "parentId": 0,
    "name": "商品中心",
    "path": "/product",
    "component": null,
    "componentName": null,
    "icon": "merchant",
    "visible": true,
    "keepAlive": true,
    "alwaysShow": true,
    "children": [
      {
        "id": 2014,
        "parentId": 2000,
        "name": "商品列表",
        "path": "spu",
        "component": "mall/product/spu/index",
        "componentName": "ProductSpu",
        "icon": "list",
        "visible": true,
        "keepAlive": true,
        "alwaysShow": true,
        "children": null
      },
      {
        "id": 2002,
        "parentId": 2000,
        "name": "商品分类",
        "path": "category",
        "component": "mall/product/category/index",
        "componentName": "ProductCategory",
        "icon": "dict",
        "visible": true,
        "keepAlive": true,
        "alwaysShow": true,
        "children": null
      },
      {
        "id": 2008,
        "parentId": 2000,
        "name": "商品品牌",
        "path": "brand",
        "component": "mall/product/brand/index",
        "componentName": "ProductBrand",
        "icon": "dashboard",
        "visible": true,
        "keepAlive": true,
        "alwaysShow": true,
        "children": null
      },
      {
        "id": 2019,
        "parentId": 2000,
        "name": "商品属性",
        "path": "property",
        "component": "mall/product/property/index",
        "componentName": "ProductProperty",
        "icon": "eye",
        "visible": true,
        "keepAlive": true,
        "alwaysShow": true,
        "children": null
      },
      {
        "id": 2025,
        "parentId": 2000,
        "name": "Banner管理",
        "path": "banner",
        "component": "mall/market/banner/index",
        "componentName": null,
        "icon": "",
        "visible": true,
        "keepAlive": true,
        "alwaysShow": true,
        "children": null
      }
    ]
  },
  {
    "id": 2072,
    "parentId": 0,
    "name": "订单中心",
    "path": "/trade",
    "component": null,
    "componentName": null,
    "icon": "order",
    "visible": true,
    "keepAlive": true,
    "alwaysShow": true,
    "children": [
      {
        "id": 2076,
        "parentId": 2072,
        "name": "订单列表",
        "path": "trade/order",
        "component": "mall/trade/order/index",
        "componentName": "TradeOrder",
        "icon": "list",
        "visible": true,
        "keepAlive": true,
        "alwaysShow": true,
        "children": null
      },
      {
        "id": 2077,
        "parentId": 2072,
        "name": "物流公司管理管理",
        "path": "express-company",
        "component": "mall/trade/expressCompany/index",
        "componentName": null,
        "icon": "",
        "visible": true,
        "keepAlive": true,
        "alwaysShow": true,
        "children": null
      },
      {
        "id": 2073,
        "parentId": 2072,
        "name": "售后退款",
        "path": "trade/after-sale",
        "component": "mall/trade/afterSale/index",
        "componentName": "TradeAfterSale",
        "icon": "education",
        "visible": true,
        "keepAlive": true,
        "alwaysShow": true,
        "children": null
      }
    ]
  },
  {
    "id": 2030,
    "parentId": 0,
    "name": "营销中心",
    "path": "/promotion",
    "component": null,
    "componentName": null,
    "icon": "rate",
    "visible": true,
    "keepAlive": true,
    "alwaysShow": true,
    "children": [
      {
        "id": 2059,
        "parentId": 2030,
        "name": "秒杀活动管理",
        "path": "seckill-activity",
        "component": "mall/promotion/seckill/seckillActivity/index",
        "componentName": "PromotionSeckillActivity",
        "icon": "time-range",
        "visible": true,
        "keepAlive": true,
        "alwaysShow": true,
        "children": null
      },
      {
        "id": 2066,
        "parentId": 2030,
        "name": "秒杀时段管理",
        "path": "seckill-time",
        "component": "mall/promotion/seckill/seckillTime/index",
        "componentName": "PromotionSeckillTime",
        "icon": "",
        "visible": false,
        "keepAlive": true,
        "alwaysShow": true,
        "children": null
      },
      {
        "id": 2032,
        "parentId": 2030,
        "name": "优惠劵",
        "path": "coupon-template",
        "component": "mall/promotion/couponTemplate/index",
        "componentName": "PromotionCouponTemplate",
        "icon": "textarea",
        "visible": true,
        "keepAlive": true,
        "alwaysShow": true,
        "children": null
      },
      {
        "id": 2038,
        "parentId": 2030,
        "name": "会员优惠劵",
        "path": "coupon",
        "component": "mall/promotion/coupon/index",
        "componentName": "PromotionCoupon",
        "icon": "",
        "visible": false,
        "keepAlive": true,
        "alwaysShow": true,
        "children": null
      },
      {
        "id": 2047,
        "parentId": 2030,
        "name": "限时折扣活动",
        "path": "discount-activity",
        "component": "mall/promotion/discountActivity/index",
        "componentName": "PromotionDiscountActivity",
        "icon": "time",
        "visible": true,
        "keepAlive": true,
        "alwaysShow": true,
        "children": null
      },
      {
        "id": 2041,
        "parentId": 2030,
        "name": "满减送活动",
        "path": "reward-activity",
        "component": "mall/promotion/rewardActivity/index",
        "componentName": "PromotionRewardActivity",
        "icon": "radio",
        "visible": true,
        "keepAlive": true,
        "alwaysShow": true,
        "children": null
      }
    ]
  },
  {
    "id": 2084,
    "parentId": 0,
    "name": "公众号管理",
    "path": "/mp",
    "component": null,
    "componentName": null,
    "icon": "wechat",
    "visible": true,
    "keepAlive": true,
    "alwaysShow": true,
    "children": [
      {
        "id": 2085,
        "parentId": 2084,
        "name": "账号管理",
        "path": "account",
        "component": "mp/account/index",
        "componentName": "MpAccount",
        "icon": "phone",
        "visible": true,
        "keepAlive": true,
        "alwaysShow": true,
        "children": null
      },
      {
        "id": 2092,
        "parentId": 2084,
        "name": "数据统计",
        "path": "statistics",
        "component": "mp/statistics/index",
        "componentName": "MpStatistics",
        "icon": "chart",
        "visible": true,
        "keepAlive": true,
        "alwaysShow": true,
        "children": null
      },
      {
        "id": 2093,
        "parentId": 2084,
        "name": "标签管理",
        "path": "tag",
        "component": "mp/tag/index",
        "componentName": "MpTag",
        "icon": "rate",
        "visible": true,
        "keepAlive": true,
        "alwaysShow": true,
        "children": null
      },
      {
        "id": 2099,
        "parentId": 2084,
        "name": "粉丝管理",
        "path": "user",
        "component": "mp/user/index",
        "componentName": "MpUser",
        "icon": "people",
        "visible": true,
        "keepAlive": true,
        "alwaysShow": true,
        "children": null
      },
      {
        "id": 2103,
        "parentId": 2084,
        "name": "消息管理",
        "path": "message",
        "component": "mp/message/index",
        "componentName": "MpMessage",
        "icon": "email",
        "visible": true,
        "keepAlive": true,
        "alwaysShow": true,
        "children": null
      },
      {
        "id": 2119,
        "parentId": 2084,
        "name": "菜单管理",
        "path": "menu",
        "component": "mp/menu/index",
        "componentName": "MpMenu",
        "icon": "button",
        "visible": true,
        "keepAlive": true,
        "alwaysShow": true,
        "children": null
      },
      {
        "id": 2120,
        "parentId": 2084,
        "name": "自动回复",
        "path": "auto-reply",
        "component": "mp/autoReply/index",
        "componentName": "MpAutoReply",
        "icon": "eye",
        "visible": true,
        "keepAlive": true,
        "alwaysShow": true,
        "children": null
      },
      {
        "id": 2113,
        "parentId": 2084,
        "name": "素材管理",
        "path": "material",
        "component": "mp/material/index",
        "componentName": "MpMaterial",
        "icon": "skill",
        "visible": true,
        "keepAlive": true,
        "alwaysShow": true,
        "children": null
      },
      {
        "id": 2108,
        "parentId": 2084,
        "name": "图文草稿箱",
        "path": "draft",
        "component": "mp/draft/index",
        "componentName": "MpDraft",
        "icon": "edit",
        "visible": true,
        "keepAlive": true,
        "alwaysShow": true,
        "children": null
      },
      {
        "id": 2104,
        "parentId": 2084,
        "name": "图文发表记录",
        "path": "free-publish",
        "component": "mp/freePublish/index",
        "componentName": "MpFreePublish",
        "icon": "education",
        "visible": true,
        "keepAlive": true,
        "alwaysShow": true,
        "children": null
      }
    ]
  }
]